postpy/__init__.py
postpy/_version.py
postpy/admin.py
postpy/base.py
postpy/connections.py
postpy/data_types.py
postpy/ddl.py
postpy/dml.py
postpy/dml_copy.py
postpy/extensions.py
postpy/fixtures.py
postpy/formatting.py
postpy/pg_encodings.py
postpy/sql.py
postpy/uuids.py
postpy-0.0.9.dist-info/DESCRIPTION.rst
postpy-0.0.9.dist-info/METADATA
postpy-0.0.9.dist-info/RECORD
postpy-0.0.9.dist-info/WHEEL
postpy-0.0.9.dist-info/metadata.json
postpy-0.0.9.dist-info/top_level.txt
